segmenter_model_zoo/__init__.py
segmenter_model_zoo/quilt_utils.py
segmenter_model_zoo/utils.py
segmenter_model_zoo/zoo.py
segmenter_model_zoo/bin/__init__.py
segmenter_model_zoo/bin/batch_dl_run.py
segmenter_model_zoo/model_wrapper/DNA_MEM_instance_basic.py
segmenter_model_zoo/model_wrapper/DNA_MEM_instance_plus_LF.py
segmenter_model_zoo/model_wrapper/DNA_MEM_instance_plus_LF_two_camera.py
segmenter_model_zoo/model_wrapper/LMNB1_morphological_production_alpha.py
segmenter_model_zoo/model_wrapper/LMNB1_morphological_with_labelfree.py
segmenter_model_zoo/model_wrapper/__init__.py
segmenter_model_zoo/model_wrapper/structure_AAVS1_100x_hipsc.py
segmenter_model_zoo/model_wrapper/structure_H2B_100x_hipsc.py
segmenter_model_zoo-0.1.0.dist-info/LICENSE
segmenter_model_zoo-0.1.0.dist-info/METADATA
segmenter_model_zoo-0.1.0.dist-info/WHEEL
segmenter_model_zoo-0.1.0.dist-info/entry_points.txt
segmenter_model_zoo-0.1.0.dist-info/top_level.txt
segmenter_model_zoo-0.1.0.dist-info/RECORD
